xterm/__init__.py
xterm/paate.py
xterm/vimpain.py
xterm/xterm.py
xterm/static/xterm/js/xterm.js
xterm/templates/xterm/xterm.html
django_xterm-0.3.3.dist-info/METADATA
django_xterm-0.3.3.dist-info/WHEEL
django_xterm-0.3.3.dist-info/entry_points.txt
django_xterm-0.3.3.dist-info/historia.json
django_xterm-0.3.3.dist-info/top_level.txt
django_xterm-0.3.3.dist-info/RECORD
