Metadata-Version: 2.4
Name: django-xterm
Version: 0.3.3
Summary: Django-pohjainen Xterm.JS-pääteyhteys
Author-email: Antti Hautaniemi <antti.hautaniemi@me.com>
License: MIT
Project-URL: Repository, https://github.com/an7oine/django-xterm.git
Requires-Python: >=3.8
Requires-Dist: django-pistoke
Requires-Dist: django-sivumedia
